MANIFEST.in
README.rst
setup.py
metzoo/__init__.py
metzoo/agent.py
metzoo/comparable.py
metzoo/errors.py
metzoo/request_info.py
metzoo_python_sdk.egg-info/PKG-INFO
metzoo_python_sdk.egg-info/SOURCES.txt
metzoo_python_sdk.egg-info/dependency_links.txt
metzoo_python_sdk.egg-info/not-zip-safe
metzoo_python_sdk.egg-info/requires.txt
metzoo_python_sdk.egg-info/top_level.txt